{
    "admin": {
        "forms": {
            "cms.empty": {
                "groups": {
                    "cms.empty.info": {
                        "priority": 100
                    },
                    "cms.empty.advanced": {
                        "priority": 300
                    },
                    "cms.dev": {
                        "priority": 6000
                    },
                    "cms.table": {
                        "priority": 7000
                    },
                    "cms.revisions": {
                        "priority": 8000
                    }
                },
                "sidebars": {
                    "default": {
                        "properties": [
                            "created",
                            "created_by",
                            "last_modified",
                            "last_modified_by"
                        ]
                    }
                }
            }
        },

        "form_groups": {
            "cms.empty.info": {
                "title": "Info",
                "show_title": false,
                "show_header": false,
                "icon": "info",
                "properties": [
                    "title"
                ],
                "priority": 100
            },
            "cms.empty.advanced": {
                "title": "Options",
                "show_title": false,
                "show_header": false,
                "icon": "cog",
                "properties": [
                    "master",
                    "in_menu",
                    "active"
                ]
            }
        },
        "dashboards": {
            "cms.empty.edit": {
                "layout": {
                    "structure": [
                        {"columns": [1]},
                        {"columns": [1]},
                        {"columns": [1]},
                        {"columns": [1]}
                    ]
                },
                "widgets": {
                    "form": {
                        "priority": 10,
                        "type": "charcoal/admin/widget/objectForm",
                        "form_ident": "cms.empty",
                        "group_display_mode": "tab"
                    }
                }
            }
        },
        "default_create_dashboard": "cms.empty.edit",
        "default_edit_dashboard": "cms.empty.edit"
    }
}
